{
	"partitions" : [
		{
			"name" : "Top",
			"pins" : [
				{
					"name" : "W1",
					"strict" : false
				},
				{
					"name" : "W2",
					"strict" : false
				},
				{
					"name" : "E1",
					"strict" : false
				},
				{
					"name" : "E2",
					"strict" : false
				},
				{
					"name" : "R1",
					"strict" : false
				},
				{
					"name" : "P1",
					"strict" : false
				},
				{
					"name" : "S1",
					"strict" : false
				},
				{
					"name" : "R2",
					"strict" : false
				},
				{
					"name" : "P2",
					"strict" : false
				},
				{
					"name" : "S2",
					"strict" : false
				}
			]
		}
	]
}